[
  {
    "id": "moug110wvpdw",
    "timestamp": "2026-05-06T19:21:33.296Z",
    "action": "login",
    "target": "Admin Panel",
    "details": "Successful login",
    "user": "admin"
  },
  {
    "id": "moug1abubw8k",
    "timestamp": "2026-05-06T19:21:45.354Z",
    "action": "login",
    "target": "Admin Panel",
    "details": "Successful login",
    "user": "admin"
  },
  {
    "id": "moug472cc0gg",
    "timestamp": "2026-05-06T19:24:01.092Z",
    "action": "login",
    "target": "Admin Panel",
    "details": "Successful login",
    "user": "admin"
  },
  {
    "id": "moug494znqom",
    "timestamp": "2026-05-06T19:24:03.779Z",
    "action": "add",
    "target": "Deploy Test",
    "details": "TV • 8 • ",
    "user": "admin"
  },
  {
    "id": "moug4l2h4mqu",
    "timestamp": "2026-05-06T19:24:19.241Z",
    "action": "login",
    "target": "Admin Panel",
    "details": "Successful login",
    "user": "admin"
  },
  {
    "id": "moug4mmq2l5t",
    "timestamp": "2026-05-06T19:24:21.266Z",
    "action": "add",
    "target": "Debug Test 123",
    "details": "TV • 8 • ",
    "user": "admin"
  },
  {
    "id": "moug51gisxi1",
    "timestamp": "2026-05-06T19:24:40.482Z",
    "action": "login",
    "target": "Admin Panel",
    "details": "Successful login",
    "user": "admin"
  },
  {
    "id": "moug534w00br",
    "timestamp": "2026-05-06T19:24:42.656Z",
    "action": "add",
    "target": "Explicit Creds Test",
    "details": "TV • 8 • ",
    "user": "admin"
  },
  {
    "id": "moug5dcgsekf",
    "timestamp": "2026-05-06T19:24:55.888Z",
    "action": "login",
    "target": "Admin Panel",
    "details": "Successful login",
    "user": "admin"
  },
  {
    "id": "moug5eupm24m",
    "timestamp": "2026-05-06T19:24:57.841Z",
    "action": "add",
    "target": "Token Test",
    "details": "TV • 8 • ",
    "user": "admin"
  },
  {
    "id": "moug5i2v6gbt",
    "timestamp": "2026-05-06T19:25:02.023Z",
    "action": "delete",
    "target": "Another",
    "details": "TV • 7.5",
    "user": "admin"
  },
  {
    "id": "moug6bav0ei0",
    "timestamp": "2026-05-06T19:25:39.895Z",
    "action": "login",
    "target": "Admin Panel",
    "details": "Successful login",
    "user": "admin"
  },
  {
    "id": "moug6dmsu2ub",
    "timestamp": "2026-05-06T19:25:42.916Z",
    "action": "add",
    "target": "Persist Test",
    "details": "TV • 8 • ",
    "user": "admin"
  },
  {
    "id": "moug76ljqjtf",
    "timestamp": "2026-05-06T19:26:20.455Z",
    "action": "login",
    "target": "Admin Panel",
    "details": "Successful login",
    "user": "admin"
  },
  {
    "id": "moug78dk9mby",
    "timestamp": "2026-05-06T19:26:22.760Z",
    "action": "add",
    "target": "VercelEnvCheck_1778095580",
    "details": "TV • 8 • ",
    "user": "admin"
  },
  {
    "id": "moug7k5qjfi8",
    "timestamp": "2026-05-06T19:26:38.030Z",
    "action": "login",
    "target": "Admin Panel",
    "details": "Successful login",
    "user": "admin"
  },
  {
    "id": "moug9x2zbq29",
    "timestamp": "2026-05-06T19:28:28.091Z",
    "action": "login",
    "target": "Admin Panel",
    "details": "Successful login",
    "user": "admin"
  },
  {
    "id": "moug9z807wjr",
    "timestamp": "2026-05-06T19:28:30.864Z",
    "action": "add",
    "target": "Final Test",
    "details": "TV • 8 • ",
    "user": "admin"
  },
  {
    "id": "mouga7ov5298",
    "timestamp": "2026-05-06T19:28:41.839Z",
    "action": "add",
    "target": "Bulk Final 1",
    "details": "TV • 7 • ",
    "user": "admin"
  },
  {
    "id": "mouga8j2lsd2",
    "timestamp": "2026-05-06T19:28:42.926Z",
    "action": "add",
    "target": "Bulk Final 2",
    "details": "TV • 7 • ",
    "user": "admin"
  },
  {
    "id": "mouga9eqdtv9",
    "timestamp": "2026-05-06T19:28:44.066Z",
    "action": "add",
    "target": "Bulk Final 3",
    "details": "TV • 7 • ",
    "user": "admin"
  },
  {
    "id": "mougacp5oxv9",
    "timestamp": "2026-05-06T19:28:48.329Z",
    "action": "delete",
    "target": "Bulk: ",
    "details": "Deleted 0 anime entries",
    "user": "admin"
  }
]